LICENSE.md
README.md
setup.py
ceotr_unittest/__init__.py
ceotr_unittest/base.py
ceotr_unittest.egg-info/PKG-INFO
ceotr_unittest.egg-info/SOURCES.txt
ceotr_unittest.egg-info/dependency_links.txt
ceotr_unittest.egg-info/requires.txt
ceotr_unittest.egg-info/top_level.txt
ceotr_unittest.egg-info/zip-safe
ceotr_unittest/test_server/__init__.py
ceotr_unittest/test_server/server.py